cbsm/__init__.py
cbsm/compartmentalisation.py
cbsm/cubing2.py
cbsm/merge.py
cbsm/overlap.py
cbsm/plot.py
cbsm/result.py
cbsm/splitting.py
cbsm/volume_calculation.py
cbsm/zone_reformation.py
cbsm/zoning.py
cbsm-0.0.5.dist-info/LICENSE.TXT
cbsm-0.0.5.dist-info/METADATA
cbsm-0.0.5.dist-info/WHEEL
cbsm-0.0.5.dist-info/top_level.txt
cbsm-0.0.5.dist-info/RECORD
